{
  "hash": "67ec6ba8",
  "configHash": "4d3e69c3",
  "lockfileHash": "f436ba5b",
  "browserHash": "46f322c6",
  "optimized": {
    "vue": {
      "src": "../../../../../node_modules/.pnpm/vue@3.5.38_typescript@5.9.3/node_modules/vue/dist/vue.runtime.esm-bundler.js",
      "file": "vue.js",
      "fileHash": "6f5bc1c2",
      "needsInterop": false
    },
    "vitepress > @vue/devtools-api": {
      "src": "../../../../../node_modules/.pnpm/@vue+devtools-api@7.7.9/node_modules/@vue/devtools-api/dist/index.js",
      "file": "vitepress___@vue_devtools-api.js",
      "fileHash": "d995fdc0",
      "needsInterop": false
    },
    "vitepress > @vueuse/core": {
      "src": "../../../../../node_modules/.pnpm/@vueuse+core@12.8.2_typescript@5.9.3/node_modules/@vueuse/core/index.mjs",
      "file": "vitepress___@vueuse_core.js",
      "fileHash": "7195e063",
      "needsInterop": false
    },
    "mermaid": {
      "src": "../../../../../node_modules/.pnpm/mermaid@11.15.0/node_modules/mermaid/dist/mermaid.core.mjs",
      "file": "mermaid.js",
      "fileHash": "668cfcf7",
      "needsInterop": false
    }
  },
  "chunks": {
    "diagram-5GNKFQAL-3V4YF5SZ": {
      "file": "diagram-5GNKFQAL-3V4YF5SZ.js"
    },
    "architectureDiagram-3BPJPVTR-H63F3KZT": {
      "file": "architectureDiagram-3BPJPVTR-H63F3KZT.js"
    },
    "diagram-KO2AKTUF-7H6WAPG3": {
      "file": "diagram-KO2AKTUF-7H6WAPG3.js"
    },
    "ishikawaDiagram-YF4QCWOH-XNA3NEVQ": {
      "file": "ishikawaDiagram-YF4QCWOH-XNA3NEVQ.js"
    },
    "vennDiagram-CIIHVFJN-KHH6DNPJ": {
      "file": "vennDiagram-CIIHVFJN-KHH6DNPJ.js"
    },
    "diagram-OG6HWLK6-56JEYISM": {
      "file": "diagram-OG6HWLK6-56JEYISM.js"
    },
    "wardleyDiagram-YWT4CUSO-PMVVLCR5": {
      "file": "wardleyDiagram-YWT4CUSO-PMVVLCR5.js"
    },
    "journeyDiagram-JHISSGLW-M4YSBARJ": {
      "file": "journeyDiagram-JHISSGLW-M4YSBARJ.js"
    },
    "timeline-definition-PNZ67QCA-355A6K5N": {
      "file": "timeline-definition-PNZ67QCA-355A6K5N.js"
    },
    "mindmap-definition-RKZ34NQL-C7SGYIGK": {
      "file": "mindmap-definition-RKZ34NQL-C7SGYIGK.js"
    },
    "kanban-definition-UN3LZRKU-JGGFIKG6": {
      "file": "kanban-definition-UN3LZRKU-JGGFIKG6.js"
    },
    "sankeyDiagram-5OEKKPKP-6UFTZFCJ": {
      "file": "sankeyDiagram-5OEKKPKP-6UFTZFCJ.js"
    },
    "diagram-LMA3HP47-ANAEZD7H": {
      "file": "diagram-LMA3HP47-ANAEZD7H.js"
    },
    "diagram-2AECGRRQ-GFOGMSD3": {
      "file": "diagram-2AECGRRQ-GFOGMSD3.js"
    },
    "blockDiagram-GPEHLZMM-KXMLGJEW": {
      "file": "blockDiagram-GPEHLZMM-KXMLGJEW.js"
    },
    "quadrantDiagram-W4KKPZXB-EJW4BBSR": {
      "file": "quadrantDiagram-W4KKPZXB-EJW4BBSR.js"
    },
    "xychartDiagram-2RQKCTM6-DZRNJ7JL": {
      "file": "xychartDiagram-2RQKCTM6-DZRNJ7JL.js"
    },
    "requirementDiagram-4Y6WPE33-ZLZN75RH": {
      "file": "requirementDiagram-4Y6WPE33-ZLZN75RH.js"
    },
    "sequenceDiagram-3UESZ5HK-SNS4F24H": {
      "file": "sequenceDiagram-3UESZ5HK-SNS4F24H.js"
    },
    "classDiagram-4FO5ZUOK-PGMTGWP4": {
      "file": "classDiagram-4FO5ZUOK-PGMTGWP4.js"
    },
    "classDiagram-v2-Q7XG4LA2-CFPAJ2Y4": {
      "file": "classDiagram-v2-Q7XG4LA2-CFPAJ2Y4.js"
    },
    "chunk-LBI2BZXV": {
      "file": "chunk-LBI2BZXV.js"
    },
    "stateDiagram-AJRCARHV-OSGUY44O": {
      "file": "stateDiagram-AJRCARHV-OSGUY44O.js"
    },
    "stateDiagram-v2-BHNVJYJU-2TZGMVUC": {
      "file": "stateDiagram-v2-BHNVJYJU-2TZGMVUC.js"
    },
    "chunk-KKRMPDMP": {
      "file": "chunk-KKRMPDMP.js"
    },
    "eventmodeling-FCH6USID-ZMWW6MLO": {
      "file": "eventmodeling-FCH6USID-ZMWW6MLO.js"
    },
    "radar-GUYGQ44K-J6RDH5HI": {
      "file": "radar-GUYGQ44K-J6RDH5HI.js"
    },
    "treemap-LRROVOQU-GEFZBNEK": {
      "file": "treemap-LRROVOQU-GEFZBNEK.js"
    },
    "wardley-L42UT6IY-ZGFODCP3": {
      "file": "wardley-L42UT6IY-ZGFODCP3.js"
    },
    "gitGraphDiagram-PVQCEYII-XMLUHYRZ": {
      "file": "gitGraphDiagram-PVQCEYII-XMLUHYRZ.js"
    },
    "chunk-62PWXD2Q": {
      "file": "chunk-62PWXD2Q.js"
    },
    "ganttDiagram-6RSMTGT7-R6FCV7FR": {
      "file": "ganttDiagram-6RSMTGT7-R6FCV7FR.js"
    },
    "infoDiagram-5YYISTIA-5EOOFAWY": {
      "file": "infoDiagram-5YYISTIA-5EOOFAWY.js"
    },
    "pieDiagram-4H26LBE5-M46MFLBO": {
      "file": "pieDiagram-4H26LBE5-M46MFLBO.js"
    },
    "chunk-QWDJPC5P": {
      "file": "chunk-QWDJPC5P.js"
    },
    "chunk-DHWMTYO4": {
      "file": "chunk-DHWMTYO4.js"
    },
    "chunk-4NDACRD3": {
      "file": "chunk-4NDACRD3.js"
    },
    "chunk-AXIY4GHK": {
      "file": "chunk-AXIY4GHK.js"
    },
    "chunk-IGCQCM2K": {
      "file": "chunk-IGCQCM2K.js"
    },
    "chunk-A4KJ3L2K": {
      "file": "chunk-A4KJ3L2K.js"
    },
    "flowDiagram-I6XJVG4X-HML6MLQA": {
      "file": "flowDiagram-I6XJVG4X-HML6MLQA.js"
    },
    "chunk-IH26HYD4": {
      "file": "chunk-IH26HYD4.js"
    },
    "erDiagram-TEJ5UH35-OGP2WHV7": {
      "file": "erDiagram-TEJ5UH35-OGP2WHV7.js"
    },
    "chunk-56C32RFY": {
      "file": "chunk-56C32RFY.js"
    },
    "chunk-MWKV3H4B": {
      "file": "chunk-MWKV3H4B.js"
    },
    "info-J43DQDTF-6SMZADRZ": {
      "file": "info-J43DQDTF-6SMZADRZ.js"
    },
    "chunk-SW7ANJBI": {
      "file": "chunk-SW7ANJBI.js"
    },
    "packet-YPE3B663-MPJIKC4P": {
      "file": "packet-YPE3B663-MPJIKC4P.js"
    },
    "chunk-TSPPW5SY": {
      "file": "chunk-TSPPW5SY.js"
    },
    "pie-LRSECV5Y-PMKGCG4H": {
      "file": "pie-LRSECV5Y-PMKGCG4H.js"
    },
    "chunk-2P2BW5G4": {
      "file": "chunk-2P2BW5G4.js"
    },
    "treeView-BLDUP644-IV3QAPUP": {
      "file": "treeView-BLDUP644-IV3QAPUP.js"
    },
    "chunk-QZPKAEQX": {
      "file": "chunk-QZPKAEQX.js"
    },
    "architecture-7EHR7CIX-ZZMSCV2Z": {
      "file": "architecture-7EHR7CIX-ZZMSCV2Z.js"
    },
    "chunk-7XWMPWPV": {
      "file": "chunk-7XWMPWPV.js"
    },
    "gitGraph-WXDBUCRP-FQWXMEC5": {
      "file": "gitGraph-WXDBUCRP-FQWXMEC5.js"
    },
    "chunk-JNTII6NV": {
      "file": "chunk-JNTII6NV.js"
    },
    "chunk-RFOENNYQ": {
      "file": "chunk-RFOENNYQ.js"
    },
    "chunk-SHEKLBLH": {
      "file": "chunk-SHEKLBLH.js"
    },
    "chunk-LWHY24BR": {
      "file": "chunk-LWHY24BR.js"
    },
    "chunk-HULI3PVB": {
      "file": "chunk-HULI3PVB.js"
    },
    "chunk-WKLSA7OE": {
      "file": "chunk-WKLSA7OE.js"
    },
    "katex-UK56OJ3U": {
      "file": "katex-UK56OJ3U.js"
    },
    "dagre-BM42HDAG-PDRDKJEX": {
      "file": "dagre-BM42HDAG-PDRDKJEX.js"
    },
    "chunk-IRFPE4L7": {
      "file": "chunk-IRFPE4L7.js"
    },
    "chunk-BDKIH4UH": {
      "file": "chunk-BDKIH4UH.js"
    },
    "chunk-BOUPWD4L": {
      "file": "chunk-BOUPWD4L.js"
    },
    "chunk-LQXLD3ZK": {
      "file": "chunk-LQXLD3ZK.js"
    },
    "chunk-NCT2D5NX": {
      "file": "chunk-NCT2D5NX.js"
    },
    "chunk-6X4A2JN3": {
      "file": "chunk-6X4A2JN3.js"
    },
    "chunk-YRJRGVAK": {
      "file": "chunk-YRJRGVAK.js"
    },
    "chunk-OQKUHHHD": {
      "file": "chunk-OQKUHHHD.js"
    },
    "chunk-EJINOF4G": {
      "file": "chunk-EJINOF4G.js"
    },
    "cose-bilkent-S5V4N54A-7EN3JICF": {
      "file": "cose-bilkent-S5V4N54A-7EN3JICF.js"
    },
    "chunk-7LQI254J": {
      "file": "chunk-7LQI254J.js"
    },
    "c4Diagram-AAUBKEIU-RVOVOTMD": {
      "file": "c4Diagram-AAUBKEIU-RVOVOTMD.js"
    },
    "chunk-AZ7EPPJT": {
      "file": "chunk-AZ7EPPJT.js"
    },
    "chunk-SDE7TEAP": {
      "file": "chunk-SDE7TEAP.js"
    },
    "chunk-E6KK2CXR": {
      "file": "chunk-E6KK2CXR.js"
    },
    "chunk-C2Z3PZYK": {
      "file": "chunk-C2Z3PZYK.js"
    },
    "chunk-H35OXIYD": {
      "file": "chunk-H35OXIYD.js"
    },
    "chunk-EQCVQC35": {
      "file": "chunk-EQCVQC35.js"
    }
  }
}